duckdb_client/__init__.py
duckdb_server_py_client-0.1.0.dist-info/LICENSE
duckdb_server_py_client-0.1.0.dist-info/METADATA
duckdb_server_py_client-0.1.0.dist-info/WHEEL
duckdb_server_py_client-0.1.0.dist-info/top_level.txt
duckdb_server_py_client-0.1.0.dist-info/RECORD
