Metadata-Version: 2.1
Name: duckdb-server-py-client
Version: 0.1.0
Summary: DuckDB HTTP客户端，提供简单的方式通过HTTP API与DuckDB服务器交互
Home-page: https://github.com/lida/duckdb-server-py-client
Author: lida
Author-email: 
Classifier: Programming Language :: Python :: 3
Classifier: License :: OSI Approved :: MIT License
Classifier: Operating System :: OS Independent
Requires-Python: >=3.6
License-File: LICENSE
Requires-Dist: requests>=2.25.0
